{"1696464000":{"newWeight":"0","newPercentage":0,"gaugeCrvApy":[0,0],"futureGaugeCrvApy":[0,0],"inflation_rate":"6161965695807970181","lpTotalSupplys":[],"gaugeTotalSupplys":[]},"1697068800":{"newWeight":"0","newPercentage":0,"gaugeCrvApy":[0,0],"futureGaugeCrvApy":[0,0],"inflation_rate":"6161965695807970181","lpTotalSupplys":[{"timestamp":1697199167,"totalSupply":"7908118358059506891384926"},{"timestamp":1697332979,"totalSupply":"7908255409633359611134046"}],"gaugeTotalSupplys":[{"timestamp":1697199167,"totalSupply":"0"}]}}